LICENSE.txt
README.md
setup.cfg
setup.py
random_typing/__init__.py
random_typing/rt.py
random_typing.egg-info/PKG-INFO
random_typing.egg-info/SOURCES.txt
random_typing.egg-info/dependency_links.txt
random_typing.egg-info/top_level.txt