Metadata-Version: 2.1
Name: random-typing
Version: 0.1
Summary: Random Typing
Home-page: https://github.com/nayakrujul/typing-tools
Author: Rujul Nayak
Author-email: rujulnayak@outlook.com
License: Apache
Download-URL: https://github.com/nayakrujul/typing-tools/archive/refs/tags/v_01.tar.gz
Keywords: random,typing,tools
Platform: UNKNOWN
Classifier: Development Status :: 3 - Alpha
Classifier: Intended Audience :: Developers
Classifier: Topic :: Software Development :: Build Tools
Classifier: License :: OSI Approved :: MIT License
Classifier: Programming Language :: Python :: 3
Classifier: Programming Language :: Python :: 3.4
Classifier: Programming Language :: Python :: 3.5
Classifier: Programming Language :: Python :: 3.6
Classifier: Programming Language :: Python :: 3.7
Classifier: Programming Language :: Python :: 3.8
Classifier: Programming Language :: Python :: 3.9
License-File: LICENSE.txt
